{
    "7": {
        "label": "7Networks_7",
        "description": "Default",
        "color": [
            205, 62, 78
        ],
        "center": [
            -9.889644261628177,
            41.19637481354246,
            21.690222845002936
        ]
    },
    "2": {
        "label": "7Networks_2",
        "description": "Somatomotor",
        "color": [
            70, 130, 180
        ],
        "center": [
            0.47275095107039533,
            -19.887481796544705,
            39.56089737421172
        ]
    },
    "4": {
        "label": "7Networks_4",
        "description": "Ventral Attention",
        "color": [
            196, 58, 250
        ],
        "center": [
            1.0635659362895353,
            -4.186303983349717,
            48.05885413655547
        ]
    },
    "1": {
        "label": "7Networks_1",
        "description": "Visual",
        "color": [
            120, 18, 134
        ],
        "center": [
            2.5343408446903197,
            -75.47710048126659,
            3.8861208563846503
        ]
    },
    "6": {
        "label": "7Networks_6",
        "description": "Frontoparietal",
        "color": [
            230, 148, 34
        ],
        "center": [
            38.09182412465299,
            33.804047640368935,
            23.391242052476045
        ]
    },
    "5": {
        "label": "7Networks_5",
        "description": "Limbic",
        "color": [
            220, 248, 164
        ],
        "center": [
            0.5848739677929728,
            12.382843147879242,
            -27.557207568434507
        ]
    },
    "0": {
        "center": null
    },
    "3": {
        "label": "7Networks_3",
        "description": "Dorsal Attention",
        "color": [
            0, 118, 14
        ],
        "center": [
            2.0098291646231843,
            -55.30227235572994,
            34.7379230014713
        ]
    }
}